{
  "config": "{\"version\":\"5.44\",\"themeCollection\":{\"baseTheme\":{\"name\":\"CY23SU04\",\"version\":\"5.46\",\"type\":2},\"customTheme\":{\"name\":\"Data-Goblins5153235488779042.json\",\"version\":\"5.46\",\"type\":1}},\"activeSectionIndex\":0,\"defaultDrillFilterOtherVisuals\":true,\"linguisticSchemaSyncVersion\":2,\"settings\":{\"useNewFilterPaneExperience\":true,\"allowChangeFilterTypes\":true,\"useStylableVisualContainerHeader\":true,\"queryLimitOption\":6,\"useEnhancedTooltips\":true,\"exportDataMode\":1,\"useDefaultAggregateDisplayName\":true},\"objects\":{\"section\":[{\"properties\":{\"verticalAlignment\":{\"expr\":{\"Literal\":{\"Value\":\"'Middle'\"}}}}}],\"outspacePane\":[{\"properties\":{\"visible\":{\"expr\":{\"Literal\":{\"Value\":\"false\"}}},\"expanded\":{\"expr\":{\"Literal\":{\"Value\":\"false\"}}}}}]}}",
  "filters": "[{\"name\":\"Filter5a0e403e65d99d1aa77e\",\"expression\":{\"Column\":{\"Expression\":{\"SourceRef\":{\"Entity\":\"Date\"}},\"Property\":\"IsThisYear (True/False)\"}},\"filter\":{\"Version\":2,\"From\":[{\"Name\":\"d\",\"Entity\":\"Date\",\"Type\":0}],\"Where\":[{\"Condition\":{\"In\":{\"Expressions\":[{\"Column\":{\"Expression\":{\"SourceRef\":{\"Source\":\"d\"}},\"Property\":\"IsThisYear (True/False)\"}}],\"Values\":[[{\"Literal\":{\"Value\":\"true\"}}]]}}}]},\"type\":\"Categorical\",\"howCreated\":1,\"objects\":{},\"isLockedInViewMode\":true}]",
  "layoutOptimization": 0,
  "resourcePackages": [
    {
      "resourcePackage": {
        "disabled": false,
        "items": [
          {
            "name": "CY23SU04",
            "path": "BaseThemes/CY23SU04.json",
            "type": 202
          }
        ],
        "name": "SharedResources",
        "type": 2
      }
    },
    {
      "resourcePackage": {
        "disabled": false,
        "items": [
          {
            "name": "Data-Goblins5153235488779042.json",
            "path": "Data-Goblins5153235488779042.json",
            "type": 201
          }
        ],
        "name": "RegisteredResources",
        "type": 1
      }
    }
  ],
  "sections": [
    {
      "config": "{}",
      "displayName": "KPI Bullet",
      "displayOption": 1,
      "filters": "[]",
      "height": 720.00,
      "name": "ReportSection84e7fa3ae6e500dd514e",
      "visualContainers": [
        {
          "config": "{\"name\":\"3da70713080701d0a01c\",\"layouts\":[{\"id\":0,\"position\":{\"x\":441.39811903980984,\"y\":217.28137202725372,\"z\":0,\"width\":375.83480565371025,\"height\":300.9673144876325,\"tabOrder\":0}}],\"singleVisual\":{\"visualType\":\"card\",\"projections\":{\"Values\":[{\"queryRef\":\"1. Measures.Count\"}]},\"prototypeQuery\":{\"Version\":2,\"From\":[{\"Name\":\" \",\"Entity\":\"1. Measures\",\"Type\":0}],\"Select\":[{\"Measure\":{\"Expression\":{\"SourceRef\":{\"Source\":\" \"}},\"Property\":\"Count\"},\"Name\":\"1. Measures.Count\",\"NativeReferenceName\":\"Count\"}],\"OrderBy\":[{\"Direction\":2,\"Expression\":{\"Measure\":{\"Expression\":{\"SourceRef\":{\"Source\":\" \"}},\"Property\":\"Count\"}}}]},\"drillFilterOtherVisuals\":true,\"hasDefaultSort\":true,\"objects\":{\"labels\":[{\"properties\":{\"color\":{\"solid\":{\"color\":{\"expr\":{\"ThemeDataColor\":{\"ColorId\":0,\"Percent\":0}}}}},\"fontSize\":{\"expr\":{\"Literal\":{\"Value\":\"48D\"}}},\"bold\":{\"expr\":{\"Literal\":{\"Value\":\"false\"}}},\"fontFamily\":{\"expr\":{\"Literal\":{\"Value\":\"'''Segoe UI Semibold'', wf_segoe-ui_semibold, helvetica, arial, sans-serif'\"}}}}}],\"categoryLabels\":[{\"properties\":{\"show\":{\"expr\":{\"Literal\":{\"Value\":\"false\"}}}}}]},\"vcObjects\":{\"title\":[{\"properties\":{\"text\":{\"expr\":{\"Literal\":{\"Value\":\"'KPI BULLET'\"}}},\"show\":{\"expr\":{\"Literal\":{\"Value\":\"true\"}}},\"titleWrap\":{\"expr\":{\"Literal\":{\"Value\":\"true\"}}},\"fontColor\":{\"solid\":{\"color\":{\"expr\":{\"ThemeDataColor\":{\"ColorId\":5,\"Percent\":-0.25}}}}},\"fontFamily\":{\"expr\":{\"Literal\":{\"Value\":\"'''Segoe UI Semibold'', wf_segoe-ui_semibold, helvetica, arial, sans-serif'\"}}}}}],\"border\":[{\"properties\":{\"show\":{\"expr\":{\"Literal\":{\"Value\":\"true\"}}},\"color\":{\"solid\":{\"color\":{\"expr\":{\"ThemeDataColor\":{\"ColorId\":5,\"Percent\":-0.25}}}}}}}],\"background\":[{\"properties\":{\"show\":{\"expr\":{\"Literal\":{\"Value\":\"true\"}}},\"color\":{\"solid\":{\"color\":{\"expr\":{\"ThemeDataColor\":{\"ColorId\":0,\"Percent\":0}}}}},\"transparency\":{\"expr\":{\"Literal\":{\"Value\":\"0D\"}}}}}],\"subTitle\":[{\"properties\":{\"text\":{\"expr\":{\"Literal\":{\"Value\":\"'TARGET COMPARISONS'\"}}},\"show\":{\"expr\":{\"Literal\":{\"Value\":\"true\"}}},\"fontColor\":{\"solid\":{\"color\":{\"expr\":{\"ThemeDataColor\":{\"ColorId\":5,\"Percent\":-0.25}}}}},\"fontSize\":{\"expr\":{\"Literal\":{\"Value\":\"11D\"}}},\"fontFamily\":{\"expr\":{\"Literal\":{\"Value\":\"'''Segoe UI Semibold'', wf_segoe-ui_semibold, helvetica, arial, sans-serif'\"}}}}}],\"visualTooltip\":[{\"properties\":{\"titleFontColor\":{\"solid\":{\"color\":{\"expr\":{\"Literal\":{\"Value\":\"'#E6DFCF'\"}}}}},\"valueFontColor\":{\"solid\":{\"color\":{\"expr\":{\"Literal\":{\"Value\":\"'#FFFFFF'\"}}}}},\"background\":{\"solid\":{\"color\":{\"expr\":{\"Literal\":{\"Value\":\"'#3B4244'\"}}}}}}}],\"visualHeader\":[{\"properties\":{\"background\":{\"solid\":{\"color\":{\"expr\":{\"Literal\":{\"Value\":\"'#F4F4F4'\"}}}}},\"border\":{\"solid\":{\"color\":{\"expr\":{\"Literal\":{\"Value\":\"'#F4F4F4'\"}}}}}}}]}}}",
          "filters": "[]",
          "height": 300.97,
          "width": 375.83,
          "x": 441.40,
          "y": 217.28,
          "z": 0.00
        },
        {
          "config": "{\"name\":\"8f5ba9b79a6b72d0331d\",\"layouts\":[{\"id\":0,\"position\":{\"x\":486.0945709281961,\"y\":296.952714535902,\"z\":1,\"width\":286.23467600700525,\"height\":189.14185639229424,\"tabOrder\":1}}],\"singleVisual\":{\"visualType\":\"barChart\",\"projections\":{\"Y\":[{\"queryRef\":\"1. Measures.Sum (CY YTD)\"}],\"Category\":[{\"queryRef\":\"Table.Boolean Dimension\",\"active\":true}]},\"prototypeQuery\":{\"Version\":2,\"From\":[{\"Name\":\" \",\"Entity\":\"1. Measures\",\"Type\":0},{\"Name\":\"t\",\"Entity\":\"Table\",\"Type\":0}],\"Select\":[{\"Measure\":{\"Expression\":{\"SourceRef\":{\"Source\":\" \"}},\"Property\":\"Sum (CY YTD)\"},\"Name\":\"1. Measures.Sum (CY YTD)\",\"NativeReferenceName\":\"Sum (CY YTD)\"},{\"Column\":{\"Expression\":{\"SourceRef\":{\"Source\":\"t\"}},\"Property\":\"Boolean Dimension\"},\"Name\":\"Table.Boolean Dimension\",\"NativeReferenceName\":\"Boolean Dimension\"}],\"OrderBy\":[{\"Direction\":2,\"Expression\":{\"Measure\":{\"Expression\":{\"SourceRef\":{\"Source\":\" \"}},\"Property\":\"Sum (CY YTD)\"}}}]},\"drillFilterOtherVisuals\":true,\"hasDefaultSort\":true,\"objects\":{\"legend\":[{\"properties\":{\"showGradientLegend\":{\"expr\":{\"Literal\":{\"Value\":\"true\"}}},\"show\":{\"expr\":{\"Literal\":{\"Value\":\"true\"}}},\"fontSize\":{\"expr\":{\"Literal\":{\"Value\":\"8D\"}}},\"fontFamily\":{\"expr\":{\"Literal\":{\"Value\":\"'''Segoe UI Semibold'', wf_segoe-ui_semibold, helvetica, arial, sans-serif'\"}}},\"position\":{\"expr\":{\"Literal\":{\"Value\":\"'TopCenter'\"}}},\"labelColor\":{\"solid\":{\"color\":{\"expr\":{\"ThemeDataColor\":{\"ColorId\":1,\"Percent\":0.6}}}}}}}],\"categoryAxis\":[{\"properties\":{\"showAxisTitle\":{\"expr\":{\"Literal\":{\"Value\":\"false\"}}},\"labelColor\":{\"solid\":{\"color\":{\"expr\":{\"Literal\":{\"Value\":\"'#59869B'\"}}}}},\"maxMarginFactor\":{\"expr\":{\"Literal\":{\"Value\":\"50L\"}}},\"switchAxisPosition\":{\"expr\":{\"Literal\":{\"Value\":\"false\"}}},\"concatenateLabels\":{\"expr\":{\"Literal\":{\"Value\":\"false\"}}},\"fontFamily\":{\"expr\":{\"Literal\":{\"Value\":\"'''Segoe UI Semibold'', wf_segoe-ui_semibold, helvetica, arial, sans-serif'\"}}},\"reverseStackOrder\":{\"expr\":{\"Literal\":{\"Value\":\"false\"}}},\"innerPadding\":{\"expr\":{\"Literal\":{\"Value\":\"0L\"}}},\"preferredCategoryWidth\":{\"expr\":{\"Literal\":{\"Value\":\"20D\"}}},\"fontSize\":{\"expr\":{\"Literal\":{\"Value\":\"14D\"}}}}}],\"valueAxis\":[{\"properties\":{\"titleText\":{\"expr\":{\"Literal\":{\"Value\":\"'Custom X-Axis TItle'\"}}},\"gridlineShow\":{\"expr\":{\"Literal\":{\"Value\":\"false\"}}},\"labelColor\":{\"solid\":{\"color\":{\"expr\":{\"Literal\":{\"Value\":\"'#1F84BB'\"}}}}},\"showAxisTitle\":{\"expr\":{\"Literal\":{\"Value\":\"false\"}}},\"titleColor\":{\"solid\":{\"color\":{\"expr\":{\"Literal\":{\"Value\":\"'#1F84BB'\"}}}}},\"titleFontFamily\":{\"expr\":{\"Literal\":{\"Value\":\"'''Segoe UI Semibold'', wf_segoe-ui_semibold, helvetica, arial, sans-serif'\"}}},\"titleFontSize\":{\"expr\":{\"Literal\":{\"Value\":\"8D\"}}},\"invertAxis\":{\"expr\":{\"Literal\":{\"Value\":\"false\"}}},\"fontSize\":{\"expr\":{\"Literal\":{\"Value\":\"8D\"}}},\"fontFamily\":{\"expr\":{\"Literal\":{\"Value\":\"'wf_standard-font, helvetica, arial, sans-serif'\"}}},\"gridlineStyle\":{\"expr\":{\"Literal\":{\"Value\":\"'dashed'\"}}},\"gridlineColor\":{\"solid\":{\"color\":{\"expr\":{\"ThemeDataColor\":{\"ColorId\":0,\"Percent\":-0.2}}}}},\"show\":{\"expr\":{\"Literal\":{\"Value\":\"false\"}}}}}],\"general\":[{\"properties\":{\"responsive\":{\"expr\":{\"Literal\":{\"Value\":\"false\"}}}}}],\"totals\":[{\"properties\":{\"show\":{\"expr\":{\"Literal\":{\"Value\":\"false\"}}},\"fontFamily\":{\"expr\":{\"Literal\":{\"Value\":\"'''Segoe UI Semibold'', wf_segoe-ui_semibold, helvetica, arial, sans-serif'\"}}},\"fontSize\":{\"expr\":{\"Literal\":{\"Value\":\"8D\"}}}}},{\"properties\":{\"color\":{\"solid\":{\"color\":{\"expr\":{\"ThemeDataColor\":{\"ColorId\":2,\"Percent\":-0.25}}}}}},\"selector\":{\"data\":[{\"dataViewWildcard\":{\"matchingOption\":1}}]}}],\"zoom\":[{\"properties\":{\"show\":{\"expr\":{\"Literal\":{\"Value\":\"false\"}}}}}],\"dataPoint\":[{\"properties\":{\"fill\":{\"solid\":{\"color\":{\"expr\":{\"Literal\":{\"Value\":\"'#74AFCC'\"}}}}}}},{\"properties\":{},\"selector\":{\"data\":[{\"dataViewWildcard\":{\"matchingOption\":1}}]}},{\"properties\":{\"fill\":{\"solid\":{\"color\":{\"expr\":{\"Literal\":{\"Value\":\"'#1F84BB'\"}}}}}},\"selector\":{\"data\":[{\"scopeId\":{\"Comparison\":{\"ComparisonKind\":0,\"Left\":{\"Column\":{\"Expression\":{\"SourceRef\":{\"Entity\":\"Table\"}},\"Property\":\"Sub-Dimension\"}},\"Right\":{\"Literal\":{\"Value\":\"'Even moar things'\"}}}}}]}},{\"properties\":{\"fill\":{\"solid\":{\"color\":{\"expr\":{\"Literal\":{\"Value\":\"'#51B1E3'\"}}}}}},\"selector\":{\"data\":[{\"scopeId\":{\"Comparison\":{\"ComparisonKind\":0,\"Left\":{\"Column\":{\"Expression\":{\"SourceRef\":{\"Entity\":\"Table\"}},\"Property\":\"Sub-Dimension\"}},\"Right\":{\"Literal\":{\"Value\":\"'More things'\"}}}}}]}},{\"properties\":{\"fill\":{\"solid\":{\"color\":{\"expr\":{\"Literal\":{\"Value\":\"'#97CFEE'\"}}}}}},\"selector\":{\"data\":[{\"scopeId\":{\"Comparison\":{\"ComparisonKind\":0,\"Left\":{\"Column\":{\"Expression\":{\"SourceRef\":{\"Entity\":\"Table\"}},\"Property\":\"Sub-Dimension\"}},\"Right\":{\"Literal\":{\"Value\":\"'No things'\"}}}}}]}},{\"properties\":{\"fill\":{\"solid\":{\"color\":{\"expr\":{\"Literal\":{\"Value\":\"'#DCEEF8'\"}}}}}},\"selector\":{\"data\":[{\"scopeId\":{\"Comparison\":{\"ComparisonKind\":0,\"Left\":{\"Column\":{\"Expression\":{\"SourceRef\":{\"Entity\":\"Table\"}},\"Property\":\"Sub-Dimension\"}},\"Right\":{\"Literal\":{\"Value\":\"'Things'\"}}}}}]}}],\"error\":[{\"properties\":{\"errorRange\":{\"kind\":\"ErrorRange\",\"explicit\":{\"isRelative\":{\"expr\":{\"Literal\":{\"Value\":\"false\"}}},\"lowerBound\":{\"expr\":{\"Measure\":{\"Expression\":{\"SourceRef\":{\"Entity\":\"1. Measures\"}},\"Property\":\"Sum (PY YTD)\"}}},\"upperBound\":{\"expr\":{\"Measure\":{\"Expression\":{\"SourceRef\":{\"Entity\":\"1. Measures\"}},\"Property\":\"Sum (PY YTD)\"}}}}}},\"selector\":{\"data\":[{\"dataViewWildcard\":{\"matchingOption\":0}}],\"metadata\":\"1. Measures.Sum (CY YTD)\",\"highlightMatching\":1}},{\"properties\":{\"enabled\":{\"expr\":{\"Literal\":{\"Value\":\"true\"}}},\"barColor\":{\"solid\":{\"color\":{\"expr\":{\"ThemeDataColor\":{\"ColorId\":1,\"Percent\":0}}}}},\"barMatchSeriesColor\":{\"expr\":{\"Literal\":{\"Value\":\"false\"}}},\"barBorderSize\":{\"expr\":{\"Literal\":{\"Value\":\"0L\"}}},\"markerSize\":{\"expr\":{\"Literal\":{\"Value\":\"10D\"}}},\"barBorderColor\":{\"solid\":{\"color\":{\"expr\":{\"ThemeDataColor\":{\"ColorId\":0,\"Percent\":0}}}}},\"barWidth\":{\"expr\":{\"Literal\":{\"Value\":\"1L\"}}},\"labelShow\":{\"expr\":{\"Literal\":{\"Value\":\"false\"}}},\"labelMatchSeriesColor\":{\"expr\":{\"Literal\":{\"Value\":\"false\"}}},\"labelFontSize\":{\"expr\":{\"Literal\":{\"Value\":\"8D\"}}},\"tooltipShow\":{\"expr\":{\"Literal\":{\"Value\":\"false\"}}},\"markerShape\":{\"expr\":{\"Literal\":{\"Value\":\"'longDash'\"}}}},\"selector\":{\"metadata\":\"1. Measures.Sum (CY YTD)\"}}],\"labels\":[{\"properties\":{\"show\":{\"expr\":{\"Literal\":{\"Value\":\"true\"}}},\"labelPosition\":{\"expr\":{\"Literal\":{\"Value\":\"'InsideBase'\"}}},\"color\":{\"solid\":{\"color\":{\"expr\":{\"Literal\":{\"Value\":\"'#2E6F94'\"}}}}},\"fontFamily\":{\"expr\":{\"Literal\":{\"Value\":\"'''Segoe UI Semibold'', wf_segoe-ui_semibold, helvetica, arial, sans-serif'\"}}},\"fontSize\":{\"expr\":{\"Literal\":{\"Value\":\"14D\"}}}}}]},\"vcObjects\":{\"title\":[{\"properties\":{\"show\":{\"expr\":{\"Literal\":{\"Value\":\"true\"}}},\"text\":{\"expr\":{\"Measure\":{\"Expression\":{\"SourceRef\":{\"Entity\":\"2. Report-Specific Objects\"}},\"Property\":\"KPI Bullet Title\"}}},\"fontColor\":{\"solid\":{\"color\":{\"expr\":{\"ThemeDataColor\":{\"ColorId\":7,\"Percent\":0}}}}},\"fontFamily\":{\"expr\":{\"Literal\":{\"Value\":\"'''Segoe UI Semibold'', wf_segoe-ui_semibold, helvetica, arial, sans-serif'\"}}},\"fontSize\":{\"expr\":{\"Literal\":{\"Value\":\"19D\"}}},\"background\":{\"solid\":{\"color\":{\"expr\":{\"Literal\":{\"Value\":\"null\"}}}}}}}],\"border\":[{\"properties\":{\"show\":{\"expr\":{\"Literal\":{\"Value\":\"false\"}}},\"color\":{\"solid\":{\"color\":{\"expr\":{\"ThemeDataColor\":{\"ColorId\":2,\"Percent\":0}}}}}}}],\"background\":[{\"properties\":{\"color\":{\"solid\":{\"color\":{\"expr\":{\"ThemeDataColor\":{\"ColorId\":0,\"Percent\":0}}}}},\"transparency\":{\"expr\":{\"Literal\":{\"Value\":\"0D\"}}},\"show\":{\"expr\":{\"Literal\":{\"Value\":\"false\"}}}}}],\"subTitle\":[{\"properties\":{\"show\":{\"expr\":{\"Literal\":{\"Value\":\"true\"}}},\"text\":{\"expr\":{\"Measure\":{\"Expression\":{\"SourceRef\":{\"Entity\":\"2. Report-Specific Objects\"}},\"Property\":\"KPI Bullet Subtitle\"}}},\"fontSize\":{\"expr\":{\"Literal\":{\"Value\":\"16D\"}}},\"fontFamily\":{\"expr\":{\"Literal\":{\"Value\":\"'''Segoe UI Semibold'', wf_segoe-ui_semibold, helvetica, arial, sans-serif'\"}}},\"fontColor\":{\"solid\":{\"color\":{\"expr\":{\"FillRule\":{\"Input\":{\"Measure\":{\"Expression\":{\"SourceRef\":{\"Entity\":\"1. Measures\"}},\"Property\":\"Sum (Δ PY YTD)\"}},\"FillRule\":{\"linearGradient2\":{\"min\":{\"color\":{\"Literal\":{\"Value\":\"'#B73A3A'\"}},\"value\":{\"Literal\":{\"Value\":\"0D\"}}},\"max\":{\"color\":{\"Literal\":{\"Value\":\"'#74AFCC'\"}},\"value\":{\"Literal\":{\"Value\":\"1D\"}}},\"nullColoringStrategy\":{\"strategy\":{\"Literal\":{\"Value\":\"'asZero'\"}}}}}}}}}}}}],\"divider\":[{\"properties\":{\"show\":{\"expr\":{\"Literal\":{\"Value\":\"false\"}}},\"color\":{\"solid\":{\"color\":{\"expr\":{\"FillRule\":{\"Input\":{\"Measure\":{\"Expression\":{\"SourceRef\":{\"Entity\":\"1. Measures\"}},\"Property\":\"Sum (Δ PY YTD)\"}},\"FillRule\":{\"linearGradient2\":{\"min\":{\"color\":{\"Literal\":{\"Value\":\"'#892c2c'\"}},\"value\":{\"Literal\":{\"Value\":\"0D\"}}},\"max\":{\"color\":{\"Literal\":{\"Value\":\"'#74AFCC'\"}},\"value\":{\"Literal\":{\"Value\":\"1D\"}}},\"nullColoringStrategy\":{\"strategy\":{\"Literal\":{\"Value\":\"'asZero'\"}}}}}}}}}},\"width\":{\"expr\":{\"Literal\":{\"Value\":\"2D\"}}}}}]}}}",
          "filters": "[{\"name\":\"Filter7e14a8b600cb23884f84\",\"expression\":{\"Column\":{\"Expression\":{\"SourceRef\":{\"Entity\":\"Table\"}},\"Property\":\"Boolean Dimension\"}},\"filter\":{\"Version\":2,\"From\":[{\"Name\":\"t\",\"Entity\":\"Table\",\"Type\":0}],\"Where\":[{\"Condition\":{\"In\":{\"Expressions\":[{\"Column\":{\"Expression\":{\"SourceRef\":{\"Source\":\"t\"}},\"Property\":\"Boolean Dimension\"}}],\"Values\":[[{\"Literal\":{\"Value\":\"'Approved'\"}}]]}}}]},\"type\":\"Categorical\",\"howCreated\":0,\"objects\":{},\"isHiddenInViewMode\":true,\"isLockedInViewMode\":true}]",
          "height": 189.14,
          "width": 286.23,
          "x": 486.09,
          "y": 296.95,
          "z": 1.00
        }
      ],
      "width": 1280.00
    }
  ],
  "theme": "Data-Goblins5153235488779042.json"
}